{
    "_comment": "Customizing bundle coverages based on the line of business, This JSON file will be used for populating the Bundle coverages on the coverage selection screen",
    "availableLines": [
        "PetLine"
    ],
    "PetLine": {
        "bundleCoverage": [
            {
                "bundleName": "Mini",
                "defaultCost": 7000,
                "defaultDeductible": 259,
                "defaultWaitingPeriod": "30 days",
                "defaultCoPay": "20%",
                "coverages": [
                    {
                        "coverageName": "Accidental death & Illness",
                        "isRequired": true,
                        "limit": 14000,
                        "deductible": 250,
                        "coPay": "30%",
                        "waitingPeriod": "30 days"
                    },
                    {
                        "coverageName": "Loss of Pet",
                        "isRequired": false,
                        "limit": 34000,
                        "deductible": 280,
                        "coPay": "40%",
                        "waitingPeriod": "30 days"
                    },
                    {
                        "coverageName": "Mortality benefit",
                        "isRequired": true,
                        "limit": 3000,
                        "deductible": 180,
                        "coPay": "10%",
                        "waitingPeriod": "15 days"
                    }
                ]
            },
            {
                "bundleName": "Micro",
                "defaultCost": 7000,
                "defaultDeductible": 259,
                "defaultWaitingPeriod": "30 days",
                "defaultCoPay": "20%",
                "coverages": [
                    {
                        "coverageName": "Advertising Expenses",
                        "isRequired": true,
                        "limit": 14000,
                        "deductible": 250,
                        "coPay": "30%",
                        "waitingPeriod": "30 days"
                    },
                    {
                        "coverageName": "Loss of Pet",
                        "isRequired": false,
                        "limit": 34000,
                        "deductible": 280,
                        "coPay": "40%",
                        "waitingPeriod": "30 days"
                    },
                    {
                        "coverageName": "Kennel & Cattery Fees",
                        "isRequired": true,
                        "limit": 3000,
                        "deductible": 180,
                        "coPay": "10%",
                        "waitingPeriod": "15 days"
                    }
                ]
            }
        ]
    }
}